{
  "info": {
    "_postman_id": "b4431ffb-f3e9-48c9-9213-e4a8c5f67825",
    "name": "Postman Beginner's Course - API Testing",
    "schema": "https://schema.getpostman.com/json/collection/v2.1.0/collection.json",
    "_exporter_id": "4939308"
  },
  "item": [
    {
      "name": "API Status",
      "event": [
        {
          "listen": "prerequest",
          "script": {
            "exec": [
              ""
            ],
            "type": "text/javascript",
            "packages": {},
            "requests": {}
          }
        },
        {
          "listen": "test",
          "script": {
            "exec": [
              "// Status code\r",
              "pm.test(\"Status is 200\", function () {\r",
              "    pm.response.to.have.status(200);\r",
              "});\r",
              "\r",
              "// Response time\r",
              "pm.test(\"Response time is under 1000 ms\", function () {\r",
              "    pm.expect(pm.response.responseTime).to.be.below(1000);\r",
              "});\r",
              "\r",
              "// Content-Type header\r",
              "pm.test(\"Content-Type is application/json\", function () {\r",
              "    pm.response.to.have.header(\"Content-Type\");\r",
              "    pm.expect(pm.response.headers.get(\"Content-Type\")).to.include(\"application/json\");\r",
              "});\r",
              "\r",
              "// Body is valid JSON\r",
              "let jsonData;\r",
              "pm.test(\"Response body is valid JSON\", function () {\r",
              "    try {\r",
              "        jsonData = pm.response.json();\r",
              "        pm.expect(jsonData).to.be.an(\"object\");\r",
              "    } catch (e) {\r",
              "        pm.expect.fail(\"Response is not valid JSON\");\r",
              "    }\r",
              "});\r",
              "\r",
              "// Body contains status = \"OK\"\r",
              "\r",
              "const response = pm.response.json();\r",
              "\r",
              "console.log(response.status);\r",
              "console.log(response['status']);\r",
              "\r",
              "pm.test('status should be OK', () => {\r",
              "    pm.expect(response.status).to.eql(\"OK\");\r",
              "})\r",
              "\r",
              "pm.test('Response body has property \"status\" equal to \"OK\"', function () {\r",
              "    pm.expect(jsonData).to.have.property(\"status\");\r",
              "    pm.expect(jsonData.status).to.be.a(\"string\");\r",
              "    pm.expect(jsonData.status).to.eql(\"OK\");\r",
              "});\r",
              "\r",
              "// Save full response JSON to environment variable\r",
              "if (typeof jsonData !== \"undefined\") {\r",
              "    pm.environment.set(\"statusResponse\", JSON.stringify(jsonData));\r",
              "}\r",
              "\r",
              "pm.execution.setNextRequest(\"List of Books\");"
            ],
            "type": "text/javascript",
            "packages": {},
            "requests": {}
          }
        }
      ],
      "request": {
        "method": "GET",
        "header": [],
        "url": {
          "raw": "{{baseUrl}}/status",
          "host": [
            "{{baseUrl}}"
          ],
          "path": [
            "status"
          ]
        }
      },
      "response": []
    },
    {
      "name": "List of Books",
      "event": [
        {
          "listen": "prerequest",
          "script": {
            "exec": [
              ""
            ],
            "type": "text/javascript",
            "packages": {},
            "requests": {}
          }
        },
        {
          "listen": "test",
          "script": {
            "exec": [
              "// Status code\r",
              "pm.test(\"Status is 200\", function () {\r",
              "    pm.response.to.have.status(200);\r",
              "});\r",
              "\r",
              "// Response time\r",
              "pm.test(\"Response time is under 1000 ms\", function () {\r",
              "    pm.expect(pm.response.responseTime).to.be.below(1000);\r",
              "});\r",
              "\r",
              "// Content-Type header\r",
              "pm.test(\"Content-Type is application/json\", function () {\r",
              "    pm.response.to.have.header(\"Content-Type\");\r",
              "    pm.expect(pm.response.headers.get(\"Content-Type\")).to.include(\"application/json\");\r",
              "});\r",
              "\r",
              "const response = pm.response.json();\r",
              "const nonFictionBooks = response.filter( (book) => book.available === true);\r",
              "const book = nonFictionBooks[0];\r",
              "\r",
              "if(book){\r",
              "    pm.globals.set(\"bookId\", book.id);\r",
              "}\r",
              "\r",
              "pm.test('Book test', () =>{\r",
              "    pm.expect(book).to.be.an('object');\r",
              "    pm.expect(book.available).to.eql(true);\r",
              "    pm.expect(book.type).to.eql('non-fiction');\r",
              "});\r",
              "\r",
              "\r",
              ""
            ],
            "type": "text/javascript",
            "packages": {},
            "requests": {}
          }
        }
      ],
      "request": {
        "method": "GET",
        "header": [],
        "url": {
          "raw": "{{baseUrl}}/books?type=non-fiction",
          "host": [
            "{{baseUrl}}"
          ],
          "path": [
            "books"
          ],
          "query": [
            {
              "key": "type",
              "value": "non-fiction"
            },
            {
              "key": "limit",
              "value": "4",
              "disabled": true
            }
          ]
        }
      },
      "response": []
    },
    {
      "name": "Book Details",
      "event": [
        {
          "listen": "test",
          "script": {
            "exec": [
              "pm.test(\"Status is 200\", function () {\r",
              "    pm.response.to.have.status(200);\r",
              "});\r",
              "\r",
              "pm.test(\"Is in stock\", function () {\r",
              "    const response = pm.response.json();\r",
              "\r",
              "    pm.expect(response['current-stock']).to.be.above(2);\r",
              "});"
            ],
            "type": "text/javascript",
            "packages": {},
            "requests": {}
          }
        }
      ],
      "request": {
        "auth": {
          "type": "noauth"
        },
        "method": "GET",
        "header": [],
        "url": {
          "raw": "{{baseUrl}}/books/:id",
          "host": [
            "{{baseUrl}}"
          ],
          "path": [
            "books",
            ":id"
          ],
          "variable": [
            {
              "key": "id",
              "value": "{{bookId}}"
            }
          ]
        }
      },
      "response": []
    },
    {
      "name": "Order Book",
      "event": [
        {
          "listen": "test",
          "script": {
            "exec": [
              "pm.test(\"Status is 201\", function () {\r",
              "    pm.response.to.have.status(201);\r",
              "});\r",
              "\r",
              "const response = pm.response.json();\r",
              "pm.globals.set('orderId', response.orderId);"
            ],
            "type": "text/javascript",
            "packages": {},
            "requests": {}
          }
        }
      ],
      "request": {
        "auth": {
          "type": "bearer",
          "bearer": [
            {
              "key": "token",
              "value": "{{accessToken}}",
              "type": "string"
            }
          ]
        },
        "method": "POST",
        "header": [],
        "body": {
          "mode": "raw",
          "raw": "{\r\n  \"bookId\": {{bookId}},\r\n  \"customerName\": \"{{$randomFullName}}\"\r\n}",
          "options": {
            "raw": {
              "language": "json"
            }
          }
        },
        "url": {
          "raw": "{{baseUrl}}/orders",
          "host": [
            "{{baseUrl}}"
          ],
          "path": [
            "orders"
          ]
        }
      },
      "response": []
    },
    {
      "name": "See all book orders",
      "event": [
        {
          "listen": "test",
          "script": {
            "exec": [
              "pm.test(\"Status is 200\", function () {\r",
              "    pm.response.to.have.status(200);\r",
              "});"
            ],
            "type": "text/javascript",
            "packages": {},
            "requests": {}
          }
        }
      ],
      "protocolProfileBehavior": {
        "disableBodyPruning": true
      },
      "request": {
        "auth": {
          "type": "bearer",
          "bearer": [
            {
              "key": "token",
              "value": "{{accessToken}}",
              "type": "string"
            }
          ]
        },
        "method": "GET",
        "header": [],
        "body": {
          "mode": "raw",
          "raw": "",
          "options": {
            "raw": {
              "language": "json"
            }
          }
        },
        "url": {
          "raw": "{{baseUrl}}/orders",
          "host": [
            "{{baseUrl}}"
          ],
          "path": [
            "orders"
          ]
        }
      },
      "response": []
    },
    {
      "name": "See one book order details",
      "event": [
        {
          "listen": "test",
          "script": {
            "exec": [
              "pm.test(\"Status is 200\", function () {\r",
              "    pm.response.to.have.status(200);\r",
              "});"
            ],
            "type": "text/javascript",
            "packages": {},
            "requests": {}
          }
        }
      ],
      "protocolProfileBehavior": {
        "disableBodyPruning": true
      },
      "request": {
        "auth": {
          "type": "bearer",
          "bearer": [
            {
              "key": "token",
              "value": "{{accessToken}}",
              "type": "string"
            }
          ]
        },
        "method": "GET",
        "header": [],
        "body": {
          "mode": "raw",
          "raw": "",
          "options": {
            "raw": {
              "language": "json"
            }
          }
        },
        "url": {
          "raw": "{{baseUrl}}/orders/:orderId",
          "host": [
            "{{baseUrl}}"
          ],
          "path": [
            "orders",
            ":orderId"
          ],
          "variable": [
            {
              "key": "orderId",
              "value": "{{orderId}}"
            }
          ]
        }
      },
      "response": []
    },
    {
      "name": "Update an order",
      "event": [
        {
          "listen": "test",
          "script": {
            "exec": [
              "pm.test(\"Status is 204\", function () {\r",
              "    pm.response.to.have.status(204);\r",
              "});"
            ],
            "type": "text/javascript",
            "packages": {},
            "requests": {}
          }
        }
      ],
      "request": {
        "auth": {
          "type": "bearer",
          "bearer": [
            {
              "key": "token",
              "value": "{{accessToken}}",
              "type": "string"
            }
          ]
        },
        "method": "PATCH",
        "header": [],
        "body": {
          "mode": "raw",
          "raw": "{\r\n  \"customerName\": \"John {{$randomLastName}}\"\r\n}",
          "options": {
            "raw": {
              "language": "json"
            }
          }
        },
        "url": {
          "raw": "{{baseUrl}}/orders/:orderId",
          "host": [
            "{{baseUrl}}"
          ],
          "path": [
            "orders",
            ":orderId"
          ],
          "variable": [
            {
              "key": "orderId",
              "value": "{{orderId}}"
            }
          ]
        }
      },
      "response": []
    },
    {
      "name": "Delete an order Copy",
      "event": [
        {
          "listen": "test",
          "script": {
            "exec": [
              "pm.test(\"Status is 204\", function () {\r",
              "    pm.response.to.have.status(204);\r",
              "});\r",
              "\r",
              "pm.execution.setNextRequest(null);"
            ],
            "type": "text/javascript",
            "packages": {},
            "requests": {}
          }
        }
      ],
      "request": {
        "auth": {
          "type": "bearer",
          "bearer": [
            {
              "key": "token",
              "value": "{{accessToken}}",
              "type": "string"
            }
          ]
        },
        "method": "DELETE",
        "header": [],
        "body": {
          "mode": "raw",
          "raw": "{\r\n  \"customerName\": \"John {{$randomLastName}}\"\r\n}",
          "options": {
            "raw": {
              "language": "json"
            }
          }
        },
        "url": {
          "raw": "{{baseUrl}}/orders/:orderId",
          "host": [
            "{{baseUrl}}"
          ],
          "path": [
            "orders",
            ":orderId"
          ],
          "variable": [
            {
              "key": "orderId",
              "value": "{{orderId}}"
            }
          ]
        }
      },
      "response": []
    },
    {
      "name": "Register API Client",
      "event": [
        {
          "listen": "test",
          "script": {
            "exec": [
              "pm.test(\"Status is 201\", function () {\r",
              "    pm.response.to.have.status(201);\r",
              "});"
            ],
            "type": "text/javascript",
            "packages": {},
            "requests": {}
          }
        }
      ],
      "request": {
        "auth": {
          "type": "noauth"
        },
        "method": "POST",
        "header": [],
        "body": {
          "mode": "raw",
          "raw": "{\r\n   \"clientName\": \"Postman\",\r\n   \"clientEmail\": \"cosmincostea@example.com\"\r\n}",
          "options": {
            "raw": {
              "language": "json"
            }
          }
        },
        "url": {
          "raw": "{{baseUrl}}/api-clients",
          "host": [
            "{{baseUrl}}"
          ],
          "path": [
            "api-clients"
          ]
        }
      },
      "response": []
    }
  ],
  "event": [
    {
      "listen": "prerequest",
      "script": {
        "type": "text/javascript",
        "packages": {},
        "requests": {},
        "exec": [
          ""
        ]
      }
    },
    {
      "listen": "test",
      "script": {
        "type": "text/javascript",
        "packages": {},
        "requests": {},
        "exec": [
          ""
        ]
      }
    }
  ],
  "variable": [
    {
      "key": "baseUrl",
      "value": "https://simple-books-api.click"
    },
    {
      "key": "accessToken",
      "value": "2e4ae0837a99e60cec449db4ed83cbc0b8b3792a1d15dbc1ffaeb0b6eb646b9e"
    }
  ]
}